LICENSE
README.md
setup.py
crlfi/__init__.py
crlfi/main.py
crlfi.egg-info/PKG-INFO
crlfi.egg-info/SOURCES.txt
crlfi.egg-info/dependency_links.txt
crlfi.egg-info/entry_points.txt
crlfi.egg-info/requires.txt
crlfi.egg-info/top_level.txt
crlfi/includes/__init__.py
crlfi/includes/bot.py
crlfi/includes/filereader.py
crlfi/includes/scan.py
crlfi/includes/writefile.py
crlfi/utils/__init__.py
crlfi/utils/configure.py
crlfi/utils/const.py
crlfi/utils/helpers.py
crlfi/utils/status.py