Metadata-Version: 2.1
Name: crlfi
Version: 0.0.6
Author: @cappriciosec
Author-email: <contact@cappriciosec.com>
Classifier: Development Status :: 1 - Planning
Classifier: Intended Audience :: Developers
Classifier: Programming Language :: Python :: 3
Classifier: Operating System :: Unix
Classifier: Operating System :: MacOS :: MacOS X
Classifier: Operating System :: Microsoft :: Windows
License-File: LICENSE
